hyqt/__init__.py
hyqt/richedit.py
hyqt/syntaxhighlighter.py
hyqt/utils.py
hyqt/widgets.py
hyqt-0.0.10.dist-info/LICENSE.txt
hyqt-0.0.10.dist-info/METADATA
hyqt-0.0.10.dist-info/WHEEL
hyqt-0.0.10.dist-info/top_level.txt
hyqt-0.0.10.dist-info/RECORD
